django_topology-1.0.2.dist-info/DESCRIPTION.rst
django_topology-1.0.2.dist-info/METADATA
django_topology-1.0.2.dist-info/RECORD
django_topology-1.0.2.dist-info/WHEEL
django_topology-1.0.2.dist-info/metadata.json
django_topology-1.0.2.dist-info/top_level.txt
topology/__init__.py
topology/apps.py
topology/choices.py
topology/extensions.py
topology/io.py
topology/managers.py
topology/models.py
topology/rules.py
topology/serializers.py
topology/signals.py
topology/urls.py
topology/utils.py
topology/utm.py
topology/validation.py
topology/views.py
topology/viewsets.py
topology/migrations/0001_initial.py
topology/migrations/0002_topologyerror_geom.py
topology/migrations/__init__.py
