Metadata-Version: 2.0
Name: django-topology
Version: 1.0.2
Summary: Geometry and  Topology utilitaries
Home-page: https://github.com/george-silva/django-topology
Author: George Silva
Author-email: george@sigmageosistemas.com.br
License: MIT
Keywords: django-topology
Platform: UNKNOWN
Classifier: Development Status :: 3 - Alpha
Classifier: Framework :: Django
Classifier: Framework :: Django :: 1.8
Classifier: Framework :: Django :: 1.9
Classifier: Framework :: Django :: 1.10
Classifier: Intended Audience :: Developers
Classifier: License :: OSI Approved :: BSD License
Classifier: Natural Language :: English
Classifier: Programming Language :: Python :: 2
Classifier: Programming Language :: Python :: 2.7
Classifier: Programming Language :: Python :: 3
Classifier: Programming Language :: Python :: 3.3
Classifier: Programming Language :: Python :: 3.4
Classifier: Programming Language :: Python :: 3.5
Requires-Dist: django
Requires-Dist: six
